__init__.py
bdd100_to_yolo/bdd100_to_yolo.py
bdd100_to_yolo-0.0.3.dist-info/LICENSE
bdd100_to_yolo-0.0.3.dist-info/METADATA
bdd100_to_yolo-0.0.3.dist-info/WHEEL
bdd100_to_yolo-0.0.3.dist-info/top_level.txt
bdd100_to_yolo-0.0.3.dist-info/RECORD
