Metadata-Version: 2.1
Name: bdd100_to_yolo
Version: 0.0.3
Summary: Invert BDD100 dataset to YOLO dataset
Author-email: Tom <xiaoTomlihail@163.com>
Maintainer-email: Tom <xiaoTomlihail@163.com>
License: MIT License
Project-URL: Repository, https://github.com/littlTom/bdd100_to_yolo.git
Keywords: BDD100 to YOLO,BDD100,YOLO,dataset,dataset invert,dataset fix
Classifier: Development Status :: 4 - Beta
Classifier: Programming Language :: Python
Requires-Python: >=3
License-File: LICENSE
Requires-Dist: tqdm
Requires-Dist: opencv-python
